revseq-1.2.0.dist-info/METADATA
revseq-1.2.0.dist-info/WHEEL
revseq-1.2.0.dist-info/entry_points.txt
revseq-1.2.0.dist-info/licenses/LICENSE
revseq/__init__.py
revseq/__main__.py
revseq-1.2.0.dist-info/RECORD
