Metadata-Version: 2.1
Name: revseq
Version: 1.2.0
Summary: reverse and/or complement dna sequence
Home-page: https://github.com/milescsmith/revseq
Author-Email: Miles Smith <mileschristiansmith@gmail.com>
License: GPL-3.0
Classifier: Programming Language :: Python :: Implementation :: CPython
Classifier: Programming Language :: Python :: Implementation :: PyPy
Classifier: Development Status :: 5 - Production/Stable
Classifier: Environment :: Console
Classifier: Intended Audience :: Science/Research
Classifier: License :: OSI Approved :: GNU General Public License v3 (GPLv3)
Classifier: Topic :: Scientific/Engineering :: Bio-Informatics
Classifier: Typing :: Typed
Project-URL: Homepage, https://github.com/milescsmith/revseq
Project-URL: Repository, https://github.com/milescsmith/revseq
Project-URL: Changelog, https://github.com/milescsmith/revseq/releases
Requires-Python: >=3.10
Requires-Dist: typer>=0.11.0
Requires-Dist: icontract>=2.6.6
Requires-Dist: rich>=13.7.1
Requires-Dist: typeguard>=4.2.1
